profilecard/__init__.py
profilecard/simple/__init__.py
profilecard/simple/config.ini
profilecard/simple/pack.py
profilecard/simple/valmanager.py
profilecard/styles/__init__.py
profilecard/styles/style1.py
profilecard/styles/style2.py
profilecard/styles/style3.py
profilecard-1.0.8.dist-info/LICENSE.md
profilecard-1.0.8.dist-info/METADATA
profilecard-1.0.8.dist-info/WHEEL
profilecard-1.0.8.dist-info/top_level.txt
profilecard-1.0.8.dist-info/RECORD
