Metadata-Version: 2.1
Name: profilecard
Version: 1.0.8
License-File: LICENSE.md
Requires-Dist: beautifulsoup4
Requires-Dist: requests
